odoo/addons/ssi_l10n_id_taxform_faktur_pajak/README.rst
odoo/addons/ssi_l10n_id_taxform_faktur_pajak/__init__.py
odoo/addons/ssi_l10n_id_taxform_faktur_pajak/__manifest__.py
odoo/addons/ssi_l10n_id_taxform_faktur_pajak/menu.xml
odoo/addons/ssi_l10n_id_taxform_faktur_pajak/data/additional_info.csv
odoo/addons/ssi_l10n_id_taxform_faktur_pajak/data/approval_template_data.xml
odoo/addons/ssi_l10n_id_taxform_faktur_pajak/data/base_automation_data.xml
odoo/addons/ssi_l10n_id_taxform_faktur_pajak/data/buyer_document_data.xml
odoo/addons/ssi_l10n_id_taxform_faktur_pajak/data/facility_stamp.csv
odoo/addons/ssi_l10n_id_taxform_faktur_pajak/data/faktur_pajak_transaction_type_data.xml
odoo/addons/ssi_l10n_id_taxform_faktur_pajak/data/ir_actions_server_data.xml
odoo/addons/ssi_l10n_id_taxform_faktur_pajak/data/ir_sequence_data.xml
odoo/addons/ssi_l10n_id_taxform_faktur_pajak/data/policy_template_data.xml
odoo/addons/ssi_l10n_id_taxform_faktur_pajak/data/res.country.csv
odoo/addons/ssi_l10n_id_taxform_faktur_pajak/data/sequence_template_data.xml
odoo/addons/ssi_l10n_id_taxform_faktur_pajak/data/uom.uom.csv
odoo/addons/ssi_l10n_id_taxform_faktur_pajak/i18n/ssi_l10n_id_taxform_faktur_pajak.pot
odoo/addons/ssi_l10n_id_taxform_faktur_pajak/migrations/14.0.3.0.0/post-migration.py
odoo/addons/ssi_l10n_id_taxform_faktur_pajak/models/__init__.py
odoo/addons/ssi_l10n_id_taxform_faktur_pajak/models/account_move.py
odoo/addons/ssi_l10n_id_taxform_faktur_pajak/models/additional_info.py
odoo/addons/ssi_l10n_id_taxform_faktur_pajak/models/buyer_document.py
odoo/addons/ssi_l10n_id_taxform_faktur_pajak/models/enofa.py
odoo/addons/ssi_l10n_id_taxform_faktur_pajak/models/enofa_number.py
odoo/addons/ssi_l10n_id_taxform_faktur_pajak/models/facility_stamp.py
odoo/addons/ssi_l10n_id_taxform_faktur_pajak/models/faktur_pajak_keluaran.py
odoo/addons/ssi_l10n_id_taxform_faktur_pajak/models/faktur_pajak_keluaran_detail.py
odoo/addons/ssi_l10n_id_taxform_faktur_pajak/models/faktur_pajak_keluaran_tax.py
odoo14_addon_ssi_l10n_id_taxform_faktur_pajak-14.0.3.12.0.dist-info/METADATA
odoo14_addon_ssi_l10n_id_taxform_faktur_pajak-14.0.3.12.0.dist-info/WHEEL
odoo14_addon_ssi_l10n_id_taxform_faktur_pajak-14.0.3.12.0.dist-info/top_level.txt
odoo14_addon_ssi_l10n_id_taxform_faktur_pajak-14.0.3.12.0.dist-info/RECORD
